[
  {
    "id": "Opsmx.StaticPolicyPlugin",
    "description": "An example of a PF4J-based plugin that provides a custom policy stage.",
    "provider": "https://github.com/opsmx",
    "releases": [
      {
        "version": "1.0.1",
        "date": "2021-07-25T16:20:59.469168Z",
        "requires": "orca>=0.0.0,deck>=0.0.0",
        "sha512sum": "96c48532eae819c031be2a063a8c84c7f13ec21443300a22fe7051ed5746d6a6d8dead073ee37ae6c7e512dfca27a8d1f2cada820b9bfadd85b9f4561459bc03",
        "state": "",
        "url": "https://github.com/OpsMx/Pf4jCustomStagePlugin/releases/download/v3.9.2-rc1/front50-v1.0.1.zip"
      }
    ]
  }
]
