[
  {
    "id": "Opsmx.VerificationGatePlugin",
    "description": "An example of a PF4J-based plugin that provides a custom policy stage.",
    "provider": "https://github.com/opsmx",
    "releases": [
      {
        "version": "1.0.1",
        "date": "2021-07-25T16:20:59.469168Z",
        "requires": "orca>=0.0.0,deck>=0.0.0",
        "sha512sum": "2db3f40bf2eda03b3c038d5f4fc47a4c6783f5a7406c3bf25ab13c1a6a61b3de3ed3bdd9e133d0c10a8335403b7b369838820d0bc6b42b50362fe5e033968f4f",
        "state": "",
        "url": "https://github.com/OpsMx/Pf4jCustomStagePlugin/releases/download/v3.9.2-rc1/orcaplugin.zip"
      }
    ]
  }
]
